{
    "location": "FuchsiaCity",
    "games": [
      "RBY",
      "RGBY"
    ],
    "pokemon": {
      "fishing": [
        {
          "rod": "Old",
          "level": "5",
          "rate": 100,
          "name": "Magikarp",
          "games": [
            "Red",
            "Aka",
            "Blue",
            "Midori",
            "Ao",
            "Yellow",
            "Ki"
          ],
          "image": "../icons/Magikarp-F.png"
        },
        {
          "rod": "Good",
          "level": "10",
          "rate": 50,
          "name": "Poliwag",
          "games": [
            "Red",
            "Aka",
            "Blue",
            "Midori",
            "Ao",
            "Yellow",
            "Ki"
          ],
          "image": "../icons/Poliwag.png"
        },
        {
          "rod": "Good",
          "level": "10",
          "rate": 50,
          "name": "Goldeen",
          "games": [
            "Red",
            "Aka",
            "Blue",
            "Midori",
            "Ao",
            "Yellow",
            "Ki"
          ],
          "image": "../icons/Goldeen-F.png"
        },
        {
          "rod": "Super",
          "level": "23",
          "rate": 25,
          "name": "Seaking",
          "games": [
            "Red",
            "Aka",
            "Blue",
            "Midori",
            "Ao"
          ],
          "image": "../icons/Seaking-F.png"
        },
        {
          "rod": "Super",
          "level": "15",
          "rate": 25,
          "name": "Krabby",
          "games": [
            "Red",
            "Aka",
            "Blue",
            "Midori",
            "Ao"
          ],
          "image": "../icons/Krabby.png"
        },
        {
          "rod": "Super",
          "level": "15",
          "rate": 25,
          "name": "Goldeen",
          "games": [
            "Red",
            "Aka",
            "Blue",
            "Midori",
            "Ao"
          ],
          "image": "../icons/Goldeen-F.png"
        },
        {
          "rod": "Super",
          "level": "15",
          "rate": 25,
          "name": "Magikarp",
          "games": [
            "Red",
            "Aka",
            "Blue",
            "Midori",
            "Ao"
          ],
          "image": "../icons/Magikarp-F.png"
        },
        {
          "rod": "Super",
          "level": "5",
          "rate": 40,
          "name": "Magikarp",
          "games": [
            "Yellow",
            "Ki"
          ],
          "image": "../icons/Magikarp-F.png"
        },
        {
          "rod": "Super",
          "level": "10",
          "rate": 30,
          "name": "Magikarp",
          "games": [
            "Yellow",
            "Ki"
          ],
          "image": "../icons/Magikarp-F.png"
        },
        {
          "rod": "Super",
          "level": "15",
          "rate": 20,
          "name": "Magikarp",
          "games": [
            "Yellow",
            "Ki"
          ],
          "image": "../icons/Magikarp-F.png"
        },
        {
          "rod": "Super",
          "level": "15",
          "rate": 10,
          "name": "Gyarados",
          "games": [
            "Yellow",
            "Ki"
          ],
          "image": "../icons/Gyarados-F.png"
        }
      ]
    },
    "items": [
      {
        "name": "Good Rod",
        "games": [
          "Red",
          "Aka",
          "Blue",
          "Midori",
          "Ao",
          "Yellow",
          "Ki"
        ],
        "location": "From the Fishing Guru's brother",
        "notes": ""
      },
      {
        "name": "HM04 Strength",
        "games": [
          "Red",
          "Aka",
          "Blue",
          "Midori",
          "Ao",
          "Yellow",
          "Ki"
        ],
        "location": "From the Safari Zone Warden after returning the Gold Teeth",
        "notes": "The Gold Teeth are found in the Safari Zone"
      },
      {
        "name": "Rare Candy",
        "games": [
          "Red",
          "Aka",
          "Blue",
          "Midori",
          "Ao",
          "Yellow",
          "Ki"
        ],
        "location": "Inside the Safari Zone Warden's house",
        "notes": "Requires Strength"
      },
      {
        "name": "TM06 Toxic",
        "games": [
          "Red",
          "Aka",
          "Blue",
          "Midori",
          "Ao",
          "Yellow",
          "Ki"
        ],
        "location": "Defeat Koga in Fuchsia Gym",
        "notes": ""
      }
    ],
    "trainers": [
      {
        "name": "Juggler",
        "games": [
          "Red",
          "Aka",
          "Blue",
          "Midori",
          "Ao",
          "Yellow",
          "Ki"
        ],
        "party": [
          "Drowzee lv.34",
          "Kadabra lv.34"
        ],
        "notes": "In Fuchsia Gym"
      },
      {
        "name": "Juggler",
        "games": [
          "Red",
          "Aka",
          "Blue",
          "Midori",
          "Ao",
          "Yellow",
          "Ki"
        ],
        "party": [
          "Hypno lv.38"
        ],
        "notes": "In Fuchsia Gym"
      },
      {
        "name": "Juggler",
        "games": [
          "Red",
          "Aka",
          "Blue",
          "Midori",
          "Ao",
          "Yellow",
          "Ki"
        ],
        "party": [
          "Drowzee lv.31",
          "Drowzee lv.31",
          "Kadabra lv.31",
          "Drowzee lv.31"
        ],
        "notes": "In Fuchsia Gym"
      },
      {
        "name": "Tamer",
        "games": [
          "Red",
          "Aka",
          "Blue",
          "Midori",
          "Ao",
          "Yellow",
          "Ki"
        ],
        "party": [
          "Arbok lv.33",
          "Sandslash lv.33",
          "Arbok lv.33"
        ],
        "notes": "In Fuchsia Gym"
      },
      {
        "name": "Tamer",
        "games": [
          "Red",
          "Aka",
          "Blue",
          "Midori",
          "Ao",
          "Yellow",
          "Ki"
        ],
        "party": [
          "Sandslash lv.34",
          "Arbok lv.34"
        ],
        "notes": "In Fuchsia Gym"
      },
      {
        "name": "Juggler",
        "games": [
          "Red",
          "Aka",
          "Blue",
          "Midori",
          "Ao",
          "Yellow",
          "Ki"
        ],
        "party": [
          "Drowzee lv.34",
          "Hypno lv.34"
        ],
        "notes": "In Fuchsia Gym"
      },
      {
        "name": "Koga",
        "games": [
          "Red",
          "Aka",
          "Blue",
          "Midori",
          "Ao"
        ],
        "party": [
          "Koffing lv.37",
          "Muk lv.39",
          "Koffing lv.37",
          "Weezing lv.43"
        ],
        "notes": "In Fuchsia Gym. Uses X Attacks"
      },
      {
        "name": "Koga",
        "games": [
          "Yellow",
          "Ki"
        ],
        "party": [
          "Venonat lv.44",
          "Venonat lv.46",
          "Venonat lv.48",
          "Venomoth lv.50"
        ],
        "notes": "In Fuchsia Gym. Uses X Attacks"
      }
    ]
  }