[{
    "location": "PokemonMansion1F",
    "games": [
      "RBY",
      "RGBY"
    ],
    "pokemon": {
      "walking": [
        {
          "level": "32",
          "rate": 20,
          "name": "Koffing",
          "games": [
            "Red",
            "Aka"
          ],
          "image": "../icons/Koffing.png"
        },
        {
          "level": "32",
          "rate": 20,
          "name": "Grimer",
          "games": [
            "Blue",
            "Midori",
            "Ao"
          ],
          "image": "../icons/Grimer.png"
        },
        {
          "level": "34",
          "rate": 20,
          "name": "Rattata",
          "games": [
            "Yellow",
            "Ki"
          ],
          "image": "../icons/Rattata-F.png"
        },
        {
          "level": "30",
          "rate": 20,
          "name": "Koffing",
          "games": [
            "Red",
            "Aka"
          ],
          "image": "../icons/Koffing.png"
        },
        {
          "level": "30",
          "rate": 20,
          "name": "Grimer",
          "games": [
            "Blue",
            "Midori",
            "Ao"
          ],
          "image": "../icons/Grimer.png"
        },
        {
          "level": "34",
          "rate": 20,
          "name": "Raticate",
          "games": [
            "Yellow",
            "Ki"
          ],
          "image": "../icons/Raticate-F.png"
        },
        {
          "level": "34",
          "rate": 15,
          "name": "Ponyta",
          "games": [
            "Red",
            "Aka",
            "Blue",
            "Midori",
            "Ao"
          ],
          "image": "../icons/Ponyta.png"
        },
        {
          "level": "23",
          "rate": 15,
          "name": "Grimer",
          "games": [
            "Yellow",
            "Ki"
          ],
          "image": "../icons/Grimer.png"
        },
        {
          "level": "30",
          "rate": 10,
          "name": "Ponyta",
          "games": [
            "Red",
            "Aka",
            "Blue",
            "Midori",
            "Ao"
          ],
          "image": "../icons/Ponyta.png"
        },
        {
          "level": "26",
          "rate": 10,
          "name": "Growlithe",
          "games": [
            "Yellow",
            "Ki"
          ],
          "image": "../icons/Growlithe.png"
        },
        {
          "level": "34",
          "rate": 10,
          "name": "Growlithe",
          "games": [
            "Red",
            "Aka",
            "Ao"
          ],
          "image": "../icons/Growlithe.png"
        },
        {
          "level": "34",
          "rate": 10,
          "name": "Vulpix",
          "games": [
            "Blue",
            "Midori"
          ],
          "image": "../icons/Vulpix.png"
        },
        {
          "level": "37",
          "rate": 10,
          "name": "Rattata",
          "games": [
            "Yellow",
            "Ki"
          ],
          "image": "../icons/Rattata-F.png"
        },
        {
          "level": "32",
          "rate": 10,
          "name": "Ponyta",
          "games": [
            "Red",
            "Aka",
            "Blue",
            "Midori",
            "Ao"
          ],
          "image": "../icons/Ponyta.png"
        },
        {
          "level": "37",
          "rate": 10,
          "name": "Raticate",
          "games": [
            "Yellow",
            "Ki"
          ],
          "image": "../icons/Raticate-F.png"
        },
        {
          "level": "30",
          "rate": 5,
          "name": "Grimer",
          "games": [
            "Red",
            "Aka"
          ],
          "image": "../icons/Grimer.png"
        },
        {
          "level": "30",
          "rate": 5,
          "name": "Koffing",
          "games": [
            "Blue",
            "Midori",
            "Ao"
          ],
          "image": "../icons/Koffing.png"
        },
        {
          "level": "30",
          "rate": 5,
          "name": "Growlithe",
          "games": [
            "Yellow",
            "Ki"
          ],
          "image": "../icons/Growlithe.png"
        },
        {
          "level": "28",
          "rate": 5,
          "name": "Ponyta",
          "games": [
            "Red",
            "Aka",
            "Blue",
            "Midori",
            "Ao"
          ],
          "image": "../icons/Ponyta.png"
        },
        {
          "level": "26",
          "rate": 5,
          "name": "Grimer",
          "games": [
            "Yellow",
            "Ki"
          ],
          "image": "../icons/Grimer.png"
        },
        {
          "level": "37",
          "rate": 4,
          "name": "Weezing",
          "games": [
            "Red",
            "Aka"
          ],
          "image": "../icons/Weezing.png"
        },
        {
          "level": "37",
          "rate": 4,
          "name": "Muk",
          "games": [
            "Blue",
            "Midori",
            "Ao"
          ],
          "image": "../icons/Muk.png"
        },
        {
          "level": "34",
          "rate": 4,
          "name": "Growlithe",
          "games": [
            "Yellow",
            "Ki"
          ],
          "image": "../icons/Growlithe.png"
        },
        {
          "level": "39",
          "rate": 1,
          "name": "Muk",
          "games": [
            "Red",
            "Aka"
          ],
          "image": "../icons/Muk.png"
        },
        {
          "level": "39",
          "rate": 1,
          "name": "Weezing",
          "games": [
            "Blue",
            "Midori",
            "Ao"
          ],
          "image": "../icons/Weezing.png"
        },
        {
          "level": "38",
          "rate": 1,
          "name": "Growlithe",
          "games": [
            "Yellow",
            "Ki"
          ],
          "image": "../icons/Growlithe.png"
        }
      ]
    },
    "items": [
      {
        "name": "Escape Rope",
        "games": [
          "Red",
          "Aka",
          "Blue",
          "Midori",
          "Ao",
          "Yellow",
          "Ki"
        ],
        "location": "In the north area",
        "notes": ""
      },
      {
        "name": "Carbos",
        "games": [
          "Red",
          "Aka",
          "Blue",
          "Midori",
          "Ao",
          "Yellow",
          "Ki"
        ],
        "location": "Near the stairs to B1F",
        "notes": ""
      },
      {
        "name": "Moon Stone",
        "games": [
          "Red",
          "Aka",
          "Blue",
          "Midori",
          "Ao",
          "Yellow",
          "Ki"
        ],
        "location": "On the fifth pillar northeast of the entrance",
        "notes": "Hidden"
      }
    ],
    "trainers": [
      {
        "name": "Scientist",
        "games": [
          "Red",
          "Aka",
          "Blue",
          "Midori",
          "Ao",
          "Yellow",
          "Ki"
        ],
        "party": [
          "Electrode lv.29",
          "Weezing lv.29"
        ],
        "notes": ""
      }
    ]
  },
  {
    "location": "PokemonMansion2F",
    "games": [
      "RBY",
      "RGBY"
    ],
    "pokemon": {
      "walking": [
        {
          "level": "32",
          "rate": 20,
          "name": "Growlithe",
          "games": [
            "Red",
            "Aka",
            "Ao"
          ],
          "image": "../icons/Growlithe.png"
        },
        {
          "level": "32",
          "rate": 20,
          "name": "Vulpix",
          "games": [
            "Blue",
            "Midori"
          ],
          "image": "../icons/Vulpix.png"
        },
        {
          "level": "37",
          "rate": 20,
          "name": "Rattata",
          "games": [
            "Yellow",
            "Ki"
          ],
          "image": "../icons/Rattata-F.png"
        },
        {
          "level": "34",
          "rate": 20,
          "name": "Koffing",
          "games": [
            "Red",
            "Aka"
          ],
          "image": "../icons/Koffing.png"
        },
        {
          "level": "34",
          "rate": 20,
          "name": "Grimer",
          "games": [
            "Blue",
            "Midori",
            "Ao"
          ],
          "image": "../icons/Grimer.png"
        },
        {
          "level": "37",
          "rate": 20,
          "name": "Raticate",
          "games": [
            "Yellow",
            "Ki"
          ],
          "image": "../icons/Raticate-F.png"
        },
        {
          "level": "34",
          "rate": 15,
          "name": "Koffing",
          "games": [
            "Red",
            "Aka"
          ],
          "image": "../icons/Koffing.png"
        },
        {
          "level": "34",
          "rate": 15,
          "name": "Grimer",
          "games": [
            "Blue",
            "Midori",
            "Ao"
          ],
          "image": "../icons/Grimer.png"
        },
        {
          "level": "26",
          "rate": 15,
          "name": "Grimer",
          "games": [
            "Yellow",
            "Ki"
          ],
          "image": "../icons/Grimer.png"
        },
        {
          "level": "30",
          "rate": 10,
          "name": "Ponyta",
          "games": [
            "Red",
            "Aka",
            "Blue",
            "Midori",
            "Ao"
          ],
          "image": "../icons/Ponyta.png"
        },
        {
          "level": "29",
          "rate": 10,
          "name": "Grimer",
          "games": [
            "Yellow",
            "Ki"
          ],
          "image": "../icons/Grimer.png"
        },
        {
          "level": "30",
          "rate": 10,
          "name": "Koffing",
          "games": [
            "Red",
            "Aka"
          ],
          "image": "../icons/Koffing.png"
        },
        {
          "level": "30",
          "rate": 10,
          "name": "Grimer",
          "games": [
            "Blue",
            "Midori",
            "Ao"
          ],
          "image": "../icons/Grimer.png"
        },
        {
          "level": "40",
          "rate": 10,
          "name": "Rattata",
          "games": [
            "Yellow",
            "Ki"
          ],
          "image": "../icons/Rattata-F.png"
        },
        {
          "level": "32",
          "rate": 10,
          "name": "Ponyta",
          "games": [
            "Red",
            "Aka",
            "Blue",
            "Midori",
            "Ao"
          ],
          "image": "../icons/Ponyta.png"
        },
        {
          "level": "40",
          "rate": 10,
          "name": "Raticate",
          "games": [
            "Yellow",
            "Ki"
          ],
          "image": "../icons/Raticate-F.png"
        },
        {
          "level": "30",
          "rate": 5,
          "name": "Grimer",
          "games": [
            "Red",
            "Aka"
          ],
          "image": "../icons/Grimer.png"
        },
        {
          "level": "30",
          "rate": 5,
          "name": "Koffing",
          "games": [
            "Blue",
            "Midori",
            "Ao"
          ],
          "image": "../icons/Koffing.png"
        },
        {
          "level": "32",
          "rate": 5,
          "name": "Grimer",
          "games": [
            "Yellow",
            "Ki"
          ],
          "image": "../icons/Grimer.png"
        },
        {
          "level": "28",
          "rate": 5,
          "name": "Ponyta",
          "games": [
            "Red",
            "Aka",
            "Blue",
            "Midori",
            "Ao"
          ],
          "image": "../icons/Ponyta.png"
        },
        {
          "level": "35",
          "rate": 5,
          "name": "Grimer",
          "games": [
            "Yellow",
            "Ki"
          ],
          "image": "../icons/Grimer.png"
        },
        {
          "level": "39",
          "rate": 4,
          "name": "Weezing",
          "games": [
            "Red",
            "Aka"
          ],
          "image": "../icons/Weezing.png"
        },
        {
          "level": "39",
          "rate": 4,
          "name": "Muk",
          "games": [
            "Blue",
            "Midori",
            "Ao"
          ],
          "image": "../icons/Muk.png"
        },
        {
          "level": "35",
          "rate": 4,
          "name": "Muk",
          "games": [
            "Yellow",
            "Ki"
          ],
          "image": "../icons/Muk.png"
        },
        {
          "level": "37",
          "rate": 1,
          "name": "Muk",
          "games": [
            "Red",
            "Aka"
          ],
          "image": "../icons/Muk.png"
        },
        {
          "level": "37",
          "rate": 1,
          "name": "Weezing",
          "games": [
            "Blue",
            "Midori",
            "Ao"
          ],
          "image": "../icons/Weezing.png"
        },
        {
          "level": "38",
          "rate": 1,
          "name": "Muk",
          "games": [
            "Yellow",
            "Ki"
          ],
          "image": "../icons/Muk.png"
        }
      ]
    },
    "items": [
	{
		"name": "Calcium",
        "games": [
          "Red",
          "Aka",
          "Blue",
          "Midori",
          "Ao",
          "Yellow",
          "Ki"
        ],
        "location": "In the northeast area",
        "notes": ""
	}
	],
    "trainers": [
      {
        "name": "Burglar",
        "games": [
          "Red",
          "Aka",
          "Blue",
          "Midori",
          "Ao",
          "Yellow",
          "Ki"
        ],
        "party": [
          "Charmander lv.34",
          "Charmeleon lv.34"
        ],
        "notes": ""
      }
    ]
  },
  {
    "location": "PokemonMansion3F",
    "games": [
      "RBY",
      "RGBY"
    ],
    "pokemon": {
      "walking": [
        {
          "level": "31",
          "rate": 20,
          "name": "Koffing",
          "games": [
            "Red",
            "Aka"
          ],
          "image": "../icons/Koffing.png"
        },
        {
          "level": "31",
          "rate": 20,
          "name": "Grimer",
          "games": [
            "Blue",
            "Midori",
            "Ao"
          ],
          "image": "../icons/Grimer.png"
        },
        {
          "level": "40",
          "rate": 20,
          "name": "Rattata",
          "games": [
            "Yellow",
            "Ki"
          ],
          "image": "../icons/Rattata-F.png"
        },
        {
          "level": "33",
          "rate": 20,
          "name": "Growlithe",
          "games": [
            "Red",
            "Aka",
            "Ao"
          ],
          "image": "../icons/Growlithe.png"
        },
        {
          "level": "40",
          "rate": 20,
          "name": "Raticate",
          "games": [
            "Yellow",
            "Ki"
          ],
          "image": "../icons/Raticate-F.png"
        },
        {
          "level": "33",
          "rate": 20,
          "name": "Vulpix",
          "games": [
            "Blue",
            "Midori"
          ],
          "image": "../icons/Vulpix.png"
        },
        {
          "level": "35",
          "rate": 15,
          "name": "Koffing",
          "games": [
            "Red",
            "Aka"
          ],
          "image": "../icons/Koffing.png"
        },
        {
          "level": "35",
          "rate": 15,
          "name": "Grimer",
          "games": [
            "Blue",
            "Midori",
            "Ao"
          ],
          "image": "../icons/Grimer.png"
        },
        {
          "level": "32",
          "rate": 15,
          "name": "Grimer",
          "games": [
            "Yellow",
            "Ki"
          ],
          "image": "../icons/Grimer.png"
        },
        {
          "level": "32",
          "rate": 10,
          "name": "Ponyta",
          "games": [
            "Red",
            "Aka",
            "Blue",
            "Midori",
            "Ao"
          ],
          "image": "../icons/Ponyta.png"
        },
        {
          "level": "35",
          "rate": 10,
          "name": "Grimer",
          "games": [
            "Yellow",
            "Ki"
          ],
          "image": "../icons/Grimer.png"
        },
        {
          "level": "34",
          "rate": 10,
          "name": "Ponyta",
          "games": [
            "Red",
            "Aka",
            "Blue",
            "Midori",
            "Ao"
          ],
          "image": "../icons/Ponyta.png"
        },
        {
          "level": "43",
          "rate": 10,
          "name": "Rattata",
          "games": [
            "Yellow",
            "Ki"
          ],
          "image": "../icons/Rattata-F.png"
        },
        {
          "level": "40",
          "rate": 10,
          "name": "Weezing",
          "games": [
            "Red",
            "Aka"
          ],
          "image": "../icons/Weezing.png"
        },
        {
          "level": "40",
          "rate": 10,
          "name": "Muk",
          "games": [
            "Blue",
            "Midori",
            "Ao"
          ],
          "image": "../icons/Muk.png"
        },
        {
          "level": "43",
          "rate": 10,
          "name": "Raticate",
          "games": [
            "Yellow",
            "Ki"
          ],
          "image": "../icons/Raticate-F.png"
        },
        {
          "level": "34",
          "rate": 5,
          "name": "Grimer",
          "games": [
            "Red",
            "Aka"
          ],
          "image": "../icons/Grimer.png"
        },
        {
          "level": "34",
          "rate": 5,
          "name": "Koffing",
          "games": [
            "Blue",
            "Midori",
            "Ao"
          ],
          "image": "../icons/Koffing.png"
        },
        {
          "level": "38",
          "rate": 5,
          "name": "Grimer",
          "games": [
            "Yellow",
            "Ki"
          ],
          "image": "../icons/Grimer.png"
        },
        {
          "level": "38",
          "rate": 5,
          "name": "Weezing",
          "games": [
            "Red",
            "Aka"
          ],
          "image": "../icons/Weezing.png"
        },
        {
          "level": "38",
          "rate": 5,
          "name": "Muk",
          "games": [
            "Blue",
            "Midori",
            "Ao"
          ],
          "image": "../icons/Muk.png"
        },
        {
          "level": "38",
          "rate": 5,
          "name": "Grimer",
          "games": [
            "Yellow",
            "Ki"
          ],
          "image": "../icons/Grimer.png"
        },
        {
          "level": "36",
          "rate": 4,
          "name": "Ponyta",
          "games": [
            "Red",
            "Aka",
            "Blue",
            "Midori",
            "Ao"
          ],
          "image": "../icons/Ponyta.png"
        },
        {
          "level": "38",
          "rate": 4,
          "name": "Muk",
          "games": [
            "Yellow",
            "Ki"
          ],
          "image": "../icons/Muk.png"
        },
        {
          "level": "42",
          "rate": 1,
          "name": "Muk",
          "games": [
            "Red",
            "Aka"
          ],
          "image": "../icons/Muk.png"
        },
        {
          "level": "42",
          "rate": 1,
          "name": "Weezing",
          "games": [
            "Blue",
            "Midori",
            "Ao"
          ],
          "image": "../icons/Weezing.png"
        },
        {
          "level": "41",
          "rate": 1,
          "name": "Muk",
          "games": [
            "Yellow",
            "Ki"
          ],
          "image": "../icons/Muk.png"
        }
      ]
    },
    "items": [
      {
        "name": "Max Potion",
        "games": [
          "Red",
          "Aka",
          "Blue",
          "Midori",
          "Ao",
          "Yellow",
          "Ki"
        ],
        "location": "In the southwest area",
        "notes": ""
      },
      {
        "name": "Iron",
        "games": [
          "Red",
          "Aka",
          "Blue",
          "Midori",
          "Ao",
          "Yellow",
          "Ki"
        ],
        "location": "In the northeast area",
        "notes": ""
      },
      {
        "name": "Max Revive",
        "games": [
          "Red",
          "Aka",
          "Blue",
          "Midori",
          "Ao",
          "Yellow",
          "Ki"
        ],
        "location": "Seven tiles north of the southwest corner, on the rubble",
        "notes": "Hidden"
      }
    ],
    "trainers": [
      {
        "name": "Burglar",
        "games": [
          "Red",
          "Aka",
          "Blue",
          "Midori",
          "Ao",
          "Yellow",
          "Ki"
        ],
        "party": [
          "Ninetales lv.38"
        ],
        "notes": ""
      },
      {
        "name": "Scientist",
        "games": [
          "Red",
          "Aka",
          "Blue",
          "Midori",
          "Ao",
          "Yellow",
          "Ki"
        ],
        "party": [
          "Magnemite lv.33",
          "Magneton lv.33",
          "Voltorb lv.33"
        ],
        "notes": ""
      }
    ]
  },
  {
    "location": "PokemonMansionB1F",
    "games": [
      "RBY",
      "RGBY"
    ],
    "pokemon": {
      "walking": [
        {
          "level": "33",
          "rate": 20,
          "name": "Koffing",
          "games": [
            "Red",
            "Aka"
          ],
          "image": "../icons/Koffing.png"
        },
        {
          "level": "33",
          "rate": 20,
          "name": "Grimer",
          "games": [
            "Blue",
            "Midori",
            "Ao"
          ],
          "image": "../icons/Grimer.png"
        },
        {
          "level": "35",
          "rate": 20,
          "name": "Grimer",
          "games": [
            "Yellow",
            "Ki"
          ],
          "image": "../icons/Grimer.png"
        },
        {
          "level": "31",
          "rate": 20,
          "name": "Koffing",
          "games": [
            "Red",
            "Aka"
          ],
          "image": "../icons/Koffing.png"
        },
        {
          "level": "31",
          "rate": 20,
          "name": "Grimer",
          "games": [
            "Blue",
            "Midori",
            "Ao"
          ],
          "image": "../icons/Grimer.png"
        },
        {
          "level": "38",
          "rate": 20,
          "name": "Grimer",
          "games": [
            "Yellow",
            "Ki"
          ],
          "image": "../icons/Grimer.png"
        },
        {
          "level": "35",
          "rate": 15,
          "name": "Growlithe",
          "games": [
            "Red",
            "Aka",
            "Ao"
          ],
          "image": "../icons/Growlithe.png"
        },
        {
          "level": "35",
          "rate": 15,
          "name": "Vulpix",
          "games": [
            "Blue",
            "Midori"
          ],
          "image": "../icons/Vulpix.png"
        },
        {
          "level": "37",
          "rate": 15,
          "name": "Raticate",
          "games": [
            "Yellow",
            "Ki"
          ],
          "image": "../icons/Raticate-F.png"
        },
        {
          "level": "32",
          "rate": 10,
          "name": "Ponyta",
          "games": [
            "Red",
            "Aka",
            "Blue",
            "Midori",
            "Ao"
          ],
          "image": "../icons/Ponyta.png"
        },
        {
          "level": "40",
          "rate": 10,
          "name": "Raticate",
          "games": [
            "Yellow",
            "Ki"
          ],
          "image": "../icons/Raticate-F.png"
        },
        {
          "level": "31",
          "rate": 10,
          "name": "Koffing",
          "games": [
            "Red",
            "Aka"
          ],
          "image": "../icons/Koffing.png"
        },
        {
          "level": "31",
          "rate": 10,
          "name": "Grimer",
          "games": [
            "Blue",
            "Midori",
            "Ao"
          ],
          "image": "../icons/Grimer.png"
        },
        {
          "level": "41",
          "rate": 10,
          "name": "Muk",
          "games": [
            "Yellow",
            "Ki"
          ],
          "image": "../icons/Muk.png"
        },
        {
          "level": "40",
          "rate": 10,
          "name": "Weezing",
          "games": [
            "Red",
            "Aka"
          ],
          "image": "../icons/Weezing.png"
        },
        {
          "level": "40",
          "rate": 10,
          "name": "Muk",
          "games": [
            "Blue",
            "Midori",
            "Ao"
          ],
          "image": "../icons/Muk.png"
        },
        {
          "level": "43",
          "rate": 10,
          "name": "Raticate",
          "games": [
            "Yellow",
            "Ki"
          ],
          "image": "../icons/Raticate-F.png"
        },
        {
          "level": "34",
          "rate": 5,
          "name": "Ponyta",
          "games": [
            "Red",
            "Aka",
            "Blue",
            "Midori",
            "Ao"
          ],
          "image": "../icons/Ponyta.png"
        },
        {
          "level": "24",
          "rate": 5,
          "name": "Ditto",
          "games": [
            "Yellow",
            "Ki"
          ],
          "image": "../icons/Ditto.png"
        },
        {
          "level": "35",
          "rate": 5,
          "name": "Grimer",
          "games": [
            "Red",
            "Aka"
          ],
          "image": "../icons/Grimer.png"
        },
        {
          "level": "35",
          "rate": 5,
          "name": "Koffing",
          "games": [
            "Blue",
            "Midori",
            "Ao"
          ],
          "image": "../icons/Koffing.png"
        },
        {
          "level": "46",
          "rate": 5,
          "name": "Raticate",
          "games": [
            "Yellow",
            "Ki"
          ],
          "image": "../icons/Raticate-F.png"
        },
        {
          "level": "42",
          "rate": 4,
          "name": "Weezing",
          "games": [
            "Red",
            "Aka"
          ],
          "image": "../icons/Weezing.png"
        },
        {
          "level": "38",
          "rate": 4,
          "name": "Magmar",
          "games": [
            "Blue",
            "Midori"
          ],
          "image": "../icons/Magmar.png"
        },
        {
          "level": "42",
          "rate": 4,
          "name": "Muk",
          "games": [
            "Ao"
          ],
          "image": "../icons/Muk.png"
        },
        {
          "level": "18",
          "rate": 4,
          "name": "Ditto",
          "games": [
            "Yellow",
            "Ki"
          ],
          "image": "../icons/Ditto.png"
        },
        {
          "level": "42",
          "rate": 1,
          "name": "Muk",
          "games": [
            "Red",
            "Aka"
          ],
          "image": "../icons/Muk.png"
        },
        {
          "level": "42",
          "rate": 1,
          "name": "Weezing",
          "games": [
            "Blue",
            "Midori",
            "Ao"
          ],
          "image": "../icons/Weezing.png"
        },
        {
          "level": "12",
          "rate": 1,
          "name": "Ditto",
          "games": [
            "Yellow",
            "Ki"
          ],
          "image": "../icons/Ditto.png"
        }
      ]
    },
    "items": [
      {
        "name": "Full Restore",
        "games": [
          "Red",
          "Aka",
          "Blue",
          "Midori",
          "Ao",
          "Yellow",
          "Ki"
        ],
        "location": "Southwest area",
        "notes": ""
      },
      {
        "name": "Secret Key",
        "games": [
          "Red",
          "Aka",
          "Blue",
          "Midori",
          "Ao",
          "Yellow",
          "Ki"
        ],
        "location": "West area",
        "notes": ""
      },
      {
        "name": "Rare Candy",
        "games": [
          "Red",
          "Aka",
          "Blue",
          "Midori",
          "Ao",
          "Yellow",
          "Ki"
        ],
        "location": "Northern area",
        "notes": ""
      },
      {
        "name": "Rare Candy",
        "games": [
          "Red",
          "Aka",
          "Blue",
          "Midori",
          "Ao",
          "Yellow",
          "Ki"
        ],
        "location": "Northwest area, near Secret Key",
        "notes": "Hidden. In Japanese Red and Green, picking up this item causes five others to disappear. Picking up any of those five will cause this one to disappear. All six are refreshed if a Fossil is given to revive in the Cinnabar Lab"
      },
      {
        "name": "TM22 Solarbeam",
        "games": [
          "Red",
          "Aka",
          "Blue",
          "Midori",
          "Ao",
          "Yellow",
          "Ki"
        ],
        "location": "Northwest area",
        "notes": ""
      },
      {
        "name": "TM14 Blizzard",
        "games": [
          "Red",
          "Aka",
          "Blue",
          "Midori",
          "Ao",
          "Yellow",
          "Ki"
        ],
        "location": "East of the southern statue",
        "notes": ""
      }
    ],
    "trainers": [
      {
        "name": "Burglar",
        "games": [
          "Red",
          "Aka",
          "Blue",
          "Midori",
          "Ao",
          "Yellow",
          "Ki"
        ],
        "party": [
          "Growlithe lv.34",
          "Ponyta lv.34"
        ],
        "notes": ""
      },
      {
        "name": "Scientist",
        "games": [
          "Red",
          "Aka",
          "Blue",
          "Midori",
          "Ao",
          "Yellow",
          "Ki"
        ],
        "party": [
          "Magnemite lv.34",
          "Electrode lv.34"
        ],
        "notes": ""
      }
    ]
  }]